ahs_orchestator_client/__init__.py
ahs_orchestator_client/api_client.py
ahs_orchestator_client/api_response.py
ahs_orchestator_client/exceptions.py
ahs_orchestator_client/rest.py
ahs_orchestator_client/security_schemes.py
ahs_orchestator_client/server.py
ahs_orchestator_client/apis/__init__.py
ahs_orchestator_client/apis/path_to_api.py
ahs_orchestator_client/apis/tag_to_api.py
ahs_orchestator_client/apis/paths/__init__.py
ahs_orchestator_client/apis/paths/api_v1_casfirmware.py
ahs_orchestator_client/apis/paths/api_v1_correctiveactions_testbed_build_number_status.py
ahs_orchestator_client/apis/paths/api_v1_correctiveactions_testbed_testbed_id.py
ahs_orchestator_client/apis/paths/api_v1_correctiveactions_testbed_testbed_id_run.py
ahs_orchestator_client/apis/paths/api_v1_device_device_id_location.py
ahs_orchestator_client/apis/paths/api_v1_health.py
ahs_orchestator_client/apis/paths/api_v1_health_env.py
ahs_orchestator_client/apis/paths/api_v1_healthchecks_testbed_build_build_number_status.py
ahs_orchestator_client/apis/paths/api_v1_healthchecks_testbed_testbed_id_run.py
ahs_orchestator_client/apis/paths/api_v1_healthcheks.py
ahs_orchestator_client/apis/paths/api_v1_healthcheks_health_check_id.py
ahs_orchestator_client/apis/paths/api_v1_healthchekssequence.py
ahs_orchestator_client/apis/paths/api_v1_healthchekssequence_health_check_definition_id.py
ahs_orchestator_client/apis/paths/api_v1_jenkins_build_build_number_status.py
ahs_orchestator_client/apis/paths/api_v1_jenkins_build_trigger.py
ahs_orchestator_client/apis/paths/api_v1_jenkins_jobs.py
ahs_orchestator_client/apis/paths/api_v1_jenkins_queue_queue_id.py
ahs_orchestator_client/apis/paths/api_v1_metric.py
ahs_orchestator_client/apis/paths/api_v1_metric_metric_testbed_testbed_id.py
ahs_orchestator_client/apis/paths/api_v1_testbed.py
ahs_orchestator_client/apis/paths/api_v1_testbed_details.py
ahs_orchestator_client/apis/paths/api_v1_testbed_status.py
ahs_orchestator_client/apis/paths/api_v1_testbed_testbed_id.py
ahs_orchestrator_client_python-1.0.3.dist-info/METADATA
ahs_orchestrator_client_python-1.0.3.dist-info/WHEEL
ahs_orchestrator_client_python-1.0.3.dist-info/top_level.txt
ahs_orchestrator_client_python-1.0.3.dist-info/RECORD
