Metadata-Version: 2.1
Name: ahs-orchestrator-client-python
Version: 1.0.3
Summary: AHS Orchestrator API
Home-page: UNKNOWN
Author: OpenAPI Generator community
Author-email: jgaddam@silabs.org
License: UNKNOWN
Keywords: OpenAPI,OpenAPI-Generator,AHS Orchestrator API
Platform: UNKNOWN
Requires-Python: >=3.6
Requires-Dist: urllib3 >=1.25.3
Requires-Dist: python-dateutil
